setup.py
Data_Transformer.egg-info/PKG-INFO
Data_Transformer.egg-info/SOURCES.txt
Data_Transformer.egg-info/dependency_links.txt
Data_Transformer.egg-info/entry_points.txt
Data_Transformer.egg-info/requires.txt
Data_Transformer.egg-info/top_level.txt
transformer/__init__.py
transformer/runner.py
transformer/xformer.py