Metadata-Version: 1.0
Name: Data-Transformer
Version: 0.1
Summary: Transforms provided input to an output, based on the transform.
Home-page: https://github.com/davydany/data_transformer
Author: David Daniel
Author-email: David.Daniel@dealertrack.com
License: BSD
Keywords: transformer xslt xml xslt transform
Platform: UNKNOWN
